{
  "meta": {
    "bookId": "853426",
    "title": "稀缺：我们是如何陷入贫穷与忙碌的",
    "author": "塞德希尔·穆来纳森",
    "translator": "魏薇,龙志勇",
    "cover": "https://cdn.weread.qq.com/weread/cover/46/YueWen_853426/t6_YueWen_853426.jpg",
    "intro": "哈佛大学终身教授、“麦克阿瑟天才奖”获得者塞得希尔·穆来纳森和普林斯顿大学心理学教授埃尔德·沙菲尔强强联合之作，继诺贝尔经济学奖获得者丹尼尔·卡尼曼《思考，快与慢》之后的又一部行为经济学重磅新作，《金融时报》2013年必读十佳商业图书。在长期研究穷人和扶贫的过程中，塞德希尔·穆来纳森发现他和穷人的焦虑竟然类似：穷人缺钱，他缺时间。在这一现象基础上，他与普林斯顿大学心理学教授埃尔德·沙菲尔进行了大量的实验室研究和现实调查，却发现了一个存在于世人中间的惊人真相：穷困之人会永远缺钱，而忙碌之人会永远缺时间。但是，进一步的研究证实：这些都是表面现象。因为即便是给穷人一笔钱，给拖延症患者一些时间，他们也无法变得富足和高效。实际上，在长期性的资源（钱、时间）稀缺中，人们已经形成了“管窥”之见，只能看到“管子”之中的事物，虽然这有可能为我们带来“专注红利”（短期的富裕或效率），但是从长远来看，这种“专心致志”反而会让我们产生“权衡式思维”，不断增加我们的带宽负担——当1元钱的价值在穷人与富人之间产生了巨大差异时，当印度金奈的街头小贩们陷入了无止境的借贷压力时，当每个人都处在多任务处理的“杂耍”状态中时……最理性的经济模型和行为方式都会变得不再符合自身的内在逻辑。最终，稀缺会俘获我们的大脑，渐渐让我们失去认知能力和执行控制力，变得更加愚笨和冲动。",
    "category": "经济理财-财经",
    "publisher": "浙江人民出版社",
    "publishTime": "2014-11-01 00:00:00",
    "isbn": "9787213063497",
    "wordCount": 0,
    "newRating": 713,
    "newRatingCount": 12031,
    "newRatingDetail": {
      "good": 8464,
      "fair": 3206,
      "poor": 361,
      "recent": 51,
      "deepV": 858,
      "myRating": "",
      "title": "值得一读"
    },
    "appLink": "weread://reading?bId=853426",
    "webLink": "https://weread.qq.com/web/reader/36b321405d05b236bb0ce7d",
    "lastSync": "2026-05-21T11:55:16Z",
    "readingProgress": "0%",
    "readingTime": "0分钟",
    "finishedDate": "",
    "noteCount": 1,
    "reviewCount": 0,
    "bookmarkCount": 0,
    "contentHash": "1554c478c4d830556818bf61ed9916fa8929ea43c180cd5641446ad6dd2c3ec5"
  },
  "chapters": [
    {
      "chapterUid": 1,
      "chapterIdx": 1,
      "title": "封面",
      "level": 1,
      "wordCount": 1,
      "price": 0,
      "paid": 0,
      "isMPChapter": 0,
      "anchors": [],
      "appLink": "weread://reading?bId=853426&chapterUid=1",
      "webLink": "https://weread.qq.com/web/reader/36b321405d05b236bb0ce7d?chapterUid=1"
    },
    {
      "chapterUid": 32,
      "chapterIdx": 2,
      "title": "版权信息",
      "level": 1,
      "wordCount": 144,
      "price": 0,
      "paid": 0,
      "isMPChapter": 0,
      "anchors": [],
      "appLink": "weread://reading?bId=853426&chapterUid=32",
      "webLink": "https://weread.qq.com/web/reader/36b321405d05b236bb0ce7d?chapterUid=32"
    },
    {
      "chapterUid": 33,
      "chapterIdx": 3,
      "title": "本书赞誉",
      "level": 1,
      "wordCount": 1757,
      "price": 0,
      "paid": 0,
      "isMPChapter": 0,
      "anchors": [],
      "appLink": "weread://reading?bId=853426&chapterUid=33",
      "webLink": "https://weread.qq.com/web/reader/36b321405d05b236bb0ce7d?chapterUid=33"
    },
    {
      "chapterUid": 34,
      "chapterIdx": 4,
      "title": "《稀缺》测试题",
      "level": 1,
      "wordCount": 2039,
      "price": 0,
      "paid": 0,
      "isMPChapter": 0,
      "anchors": [],
      "appLink": "weread://reading?bId=853426&chapterUid=34",
      "webLink": "https://weread.qq.com/web/reader/36b321405d05b236bb0ce7d?chapterUid=34"
    },
    {
      "chapterUid": 35,
      "chapterIdx": 5,
      "title": "引言 资源稀缺不可怕，就怕有稀缺心态",
      "level": 1,
      "wordCount": 11713,
      "price": 0,
      "paid": 0,
      "isMPChapter": 0,
      "anchors": [
        {
          "title": "稀缺俘获大脑",
          "anchor": "sigil_toc_id_1",
          "level": 2
        },
        {
          "title": "经济学研究稀缺，但不触及心态",
          "anchor": "sigil_toc_id_2",
          "level": 2
        },
        {
          "title": "正在发展中的稀缺科学",
          "anchor": "sigil_toc_id_3",
          "level": 2
        }
      ],
      "appLink": "weread://reading?bId=853426&chapterUid=35",
      "webLink": "https://weread.qq.com/web/reader/36b321405d05b236bb0ce7d?chapterUid=35"
    },
    {
      "chapterUid": 36,
      "chapterIdx": 6,
      "title": "第一部分 稀缺心态是一切稀缺的根源",
      "level": 1,
      "wordCount": 17,
      "price": 0,
      "paid": 0,
      "isMPChapter": 0,
      "anchors": [],
      "appLink": "weread://reading?bId=853426&chapterUid=36",
      "webLink": "https://weread.qq.com/web/reader/36b321405d05b236bb0ce7d?chapterUid=36"
    },
    {
      "chapterUid": 37,
      "chapterIdx": 7,
      "title": "第1章 专注的“得”与管窥的“失”",
      "level": 2,
      "wordCount": 152,
      "price": 0,
      "paid": 0,
      "isMPChapter": 0,
      "anchors": [],
      "appLink": "weread://reading?bId=853426&chapterUid=37",
      "webLink": "https://weread.qq.com/web/reader/36b321405d05b236bb0ce7d?chapterUid=37"
    },
    {
      "chapterUid": 38,
      "chapterIdx": 8,
      "title": "资源稀缺换来了专注与回报",
      "level": 3,
      "wordCount": 15124,
      "price": 0,
      "paid": 0,
      "isMPChapter": 0,
      "anchors": [
        {
          "title": "资源稀缺换来了专注与回报",
          "anchor": "sigil_toc_id_4",
          "level": 3
        },
        {
          "title": "专注红利",
          "anchor": "sigil_toc_id_5",
          "level": 3
        },
        {
          "title": "管窥",
          "anchor": "sigil_toc_id_6",
          "level": 3
        },
        {
          "title": "管窥所导致的忽视",
          "anchor": "sigil_toc_id_7",
          "level": 3
        },
        {
          "title": "管窥负担",
          "anchor": "sigil_toc_id_8",
          "level": 3
        }
      ],
      "appLink": "weread://reading?bId=853426&chapterUid=38",
      "webLink": "https://weread.qq.com/web/reader/36b321405d05b236bb0ce7d?chapterUid=38"
    },
    {
      "chapterUid": 39,
      "chapterIdx": 9,
      "title": "第2章 带宽负担会降低人的智商",
      "level": 2,
      "wordCount": 155,
      "price": -1,
      "paid": 0,
      "isMPChapter": 0,
      "anchors": [],
      "appLink": "weread://reading?bId=853426&chapterUid=39",
      "webLink": "https://weread.qq.com/web/reader/36b321405d05b236bb0ce7d?chapterUid=39"
    },
    {
      "chapterUid": 40,
      "chapterIdx": 10,
      "title": "“噪声”干扰了我们的思想",
      "level": 3,
      "wordCount": 20308,
      "price": -1,
      "paid": 0,
      "isMPChapter": 0,
      "anchors": [
        {
          "title": "“噪声”干扰了我们的思想",
          "anchor": "sigil_toc_id_9",
          "level": 3
        },
        {
          "title": "带宽负担1——认知能力",
          "anchor": "sigil_toc_id_10",
          "level": 3
        },
        {
          "title": "带宽负担2——执行控制力",
          "anchor": "sigil_toc_id_11",
          "level": 3
        },
        {
          "title": "收割前后的印度农民",
          "anchor": "sigil_toc_id_12",
          "level": 3
        },
        {
          "title": "其他形式的稀缺",
          "anchor": "sigil_toc_id_13",
          "level": 3
        },
        {
          "title": "稀缺，完全不同于压力和忧虑",
          "anchor": "sigil_toc_id_14",
          "level": 3
        },
        {
          "title": "稀缺让人变笨和更加冲动",
          "anchor": "sigil_toc_id_15",
          "level": 3
        }
      ],
      "appLink": "weread://reading?bId=853426&chapterUid=40",
      "webLink": "https://weread.qq.com/web/reader/36b321405d05b236bb0ce7d?chapterUid=40"
    },
    {
      "chapterUid": 41,
      "chapterIdx": 11,
      "title": "第二部分 贫穷和忙碌是如何让“带宽”变窄的",
      "level": 1,
      "wordCount": 21,
      "price": -1,
      "paid": 0,
      "isMPChapter": 0,
      "anchors": [],
      "appLink": "weread://reading?bId=853426&chapterUid=41",
      "webLink": "https://weread.qq.com/web/reader/36b321405d05b236bb0ce7d?chapterUid=41"
    },
    {
      "chapterUid": 42,
      "chapterIdx": 12,
      "title": "第3章 装箱、余闲和权衡式思维",
      "level": 2,
      "wordCount": 161,
      "price": -1,
      "paid": 0,
      "isMPChapter": 0,
      "anchors": [],
      "appLink": "weread://reading?bId=853426&chapterUid=42",
      "webLink": "https://weread.qq.com/web/reader/36b321405d05b236bb0ce7d?chapterUid=42"
    },
    {
      "chapterUid": 43,
      "chapterIdx": 13,
      "title": "权衡式思维",
      "level": 3,
      "wordCount": 13602,
      "price": -1,
      "paid": 0,
      "isMPChapter": 0,
      "anchors": [
        {
          "title": "余闲",
          "anchor": "sigil_toc_id_16",
          "level": 3
        },
        {
          "title": "穷蜜蜂与富泥蜂",
          "anchor": "sigil_toc_id_17",
          "level": 3
        },
        {
          "title": "余闲心态下的购买行为",
          "anchor": "sigil_toc_id_18",
          "level": 3
        },
        {
          "title": "没有余闲时犯错，后果很严重",
          "anchor": "sigil_toc_id_19",
          "level": 3
        },
        {
          "title": "稀缺的本质就是没有余闲",
          "anchor": "sigil_toc_id_20",
          "level": 3
        }
      ],
      "appLink": "weread://reading?bId=853426&chapterUid=43",
      "webLink": "https://weread.qq.com/web/reader/36b321405d05b236bb0ce7d?chapterUid=43"
    },
    {
      "chapterUid": 44,
      "chapterIdx": 14,
      "title": "第4章 行为经济学告诉我们的道理",
      "level": 2,
      "wordCount": 152,
      "price": -1,
      "paid": 0,
      "isMPChapter": 0,
      "anchors": [],
      "appLink": "weread://reading?bId=853426&chapterUid=44",
      "webLink": "https://weread.qq.com/web/reader/36b321405d05b236bb0ce7d?chapterUid=44"
    },
    {
      "chapterUid": 45,
      "chapterIdx": 15,
      "title": "50美元，在穷人和富人眼中的价值不一",
      "level": 3,
      "wordCount": 12762,
      "price": -1,
      "paid": 0,
      "isMPChapter": 0,
      "anchors": [
        {
          "title": "50美元，在穷人和富人眼中的价值不一",
          "anchor": "sigil_toc_id_21",
          "level": 3
        },
        {
          "title": "知觉的相对性",
          "anchor": "sigil_toc_id_22",
          "level": 3
        },
        {
          "title": "1美元的真正价值",
          "anchor": "sigil_toc_id_23",
          "level": 3
        },
        {
          "title": "识解",
          "anchor": "sigil_toc_id_24",
          "level": 3
        },
        {
          "title": "机会成本",
          "anchor": "sigil_toc_id_25",
          "level": 3
        }
      ],
      "appLink": "weread://reading?bId=853426&chapterUid=45",
      "webLink": "https://weread.qq.com/web/reader/36b321405d05b236bb0ce7d?chapterUid=45"
    },
    {
      "chapterUid": 46,
      "chapterIdx": 16,
      "title": "第5章 借用与短视",
      "level": 2,
      "wordCount": 157,
      "price": -1,
      "paid": 0,
      "isMPChapter": 0,
      "anchors": [],
      "appLink": "weread://reading?bId=853426&chapterUid=46",
      "webLink": "https://weread.qq.com/web/reader/36b321405d05b236bb0ce7d?chapterUid=46"
    },
    {
      "chapterUid": 47,
      "chapterIdx": 17,
      "title": "管窥与借用",
      "level": 3,
      "wordCount": 11960,
      "price": -1,
      "paid": 0,
      "isMPChapter": 0,
      "anchors": [
        {
          "title": "管窥与借用",
          "anchor": "sigil_toc_id_26",
          "level": 3
        },
        {
          "title": "《家庭问答》的启示",
          "anchor": "sigil_toc_id_27",
          "level": 3
        },
        {
          "title": "忽视未来",
          "anchor": "sigil_toc_id_28",
          "level": 3
        },
        {
          "title": "无力规划",
          "anchor": "sigil_toc_id_29",
          "level": 3
        }
      ],
      "appLink": "weread://reading?bId=853426&chapterUid=47",
      "webLink": "https://weread.qq.com/web/reader/36b321405d05b236bb0ce7d?chapterUid=47"
    },
    {
      "chapterUid": 48,
      "chapterIdx": 18,
      "title": "第6章 稀缺陷阱",
      "level": 2,
      "wordCount": 178,
      "price": -1,
      "paid": 0,
      "isMPChapter": 0,
      "anchors": [],
      "appLink": "weread://reading?bId=853426&chapterUid=48",
      "webLink": "https://weread.qq.com/web/reader/36b321405d05b236bb0ce7d?chapterUid=48"
    },
    {
      "chapterUid": 49,
      "chapterIdx": 19,
      "title": "停不下来的杂耍",
      "level": 3,
      "wordCount": 16147,
      "price": -1,
      "paid": 0,
      "isMPChapter": 0,
      "anchors": [
        {
          "title": "停不下来的杂耍",
          "anchor": "sigil_toc_id_30",
          "level": 3
        },
        {
          "title": "逃离",
          "anchor": "sigil_toc_id_31",
          "level": 3
        },
        {
          "title": "问题的根源",
          "anchor": "sigil_toc_id_32",
          "level": 3
        },
        {
          "title": "余闲，应对突发事件的利器",
          "anchor": "sigil_toc_id_33",
          "level": 3
        },
        {
          "title": "贫穷始于富足",
          "anchor": "sigil_toc_id_34",
          "level": 3
        },
        {
          "title": "孤独就是社交稀缺",
          "anchor": "sigil_toc_id_35",
          "level": 3
        },
        {
          "title": "改变心态，逃离稀缺陷阱的唯一希望",
          "anchor": "sigil_toc_id_36",
          "level": 3
        }
      ],
      "appLink": "weread://reading?bId=853426&chapterUid=49",
      "webLink": "https://weread.qq.com/web/reader/36b321405d05b236bb0ce7d?chapterUid=49"
    },
    {
      "chapterUid": 50,
      "chapterIdx": 20,
      "title": "第7章 穷人为什么穷",
      "level": 2,
      "wordCount": 128,
      "price": -1,
      "paid": 0,
      "isMPChapter": 0,
      "anchors": [],
      "appLink": "weread://reading?bId=853426&chapterUid=50",
      "webLink": "https://weread.qq.com/web/reader/36b321405d05b236bb0ce7d?chapterUid=50"
    },
    {
      "chapterUid": 51,
      "chapterIdx": 21,
      "title": "“最后一公里”问题",
      "level": 3,
      "wordCount": 11979,
      "price": -1,
      "paid": 0,
      "isMPChapter": 0,
      "anchors": [
        {
          "title": "“最后一公里”问题",
          "anchor": "sigil_toc_id_37",
          "level": 3
        },
        {
          "title": "无能可以导致贫穷，贫穷也可以导致无能",
          "anchor": "sigil_toc_id_38",
          "level": 3
        },
        {
          "title": "大脑自由才能成为合格家长",
          "anchor": "sigil_toc_id_39",
          "level": 3
        },
        {
          "title": "穷人缺钱又缺带宽",
          "anchor": "sigil_toc_id_40",
          "level": 3
        },
        {
          "title": "带宽负担导致智力下降",
          "anchor": "sigil_toc_id_41",
          "level": 3
        }
      ],
      "appLink": "weread://reading?bId=853426&chapterUid=51",
      "webLink": "https://weread.qq.com/web/reader/36b321405d05b236bb0ce7d?chapterUid=51"
    },
    {
      "chapterUid": 52,
      "chapterIdx": 22,
      "title": "第三部分 如何从稀缺走向富足",
      "level": 1,
      "wordCount": 14,
      "price": -1,
      "paid": 0,
      "isMPChapter": 0,
      "anchors": [],
      "appLink": "weread://reading?bId=853426&chapterUid=52",
      "webLink": "https://weread.qq.com/web/reader/36b321405d05b236bb0ce7d?chapterUid=52"
    },
    {
      "chapterUid": 53,
      "chapterIdx": 23,
      "title": "第8章 如何让穷人摆脱贫穷",
      "level": 2,
      "wordCount": 149,
      "price": -1,
      "paid": 0,
      "isMPChapter": 0,
      "anchors": [],
      "appLink": "weread://reading?bId=853426&chapterUid=53",
      "webLink": "https://weread.qq.com/web/reader/36b321405d05b236bb0ce7d?chapterUid=53"
    },
    {
      "chapterUid": 54,
      "chapterIdx": 24,
      "title": "包容穷人的不当行为",
      "level": 3,
      "wordCount": 11184,
      "price": -1,
      "paid": 0,
      "isMPChapter": 0,
      "anchors": [
        {
          "title": "让“警报”来得更早些",
          "anchor": "sigil_toc_id_42",
          "level": 3
        },
        {
          "title": "节省带宽的方法才是好方法",
          "anchor": "sigil_toc_id_43",
          "level": 3
        },
        {
          "title": "带宽可以构建",
          "anchor": "sigil_toc_id_44",
          "level": 3
        },
        {
          "title": "扶贫是个长期项目",
          "anchor": "sigil_toc_id_45",
          "level": 3
        }
      ],
      "appLink": "weread://reading?bId=853426&chapterUid=54",
      "webLink": "https://weread.qq.com/web/reader/36b321405d05b236bb0ce7d?chapterUid=54"
    },
    {
      "chapterUid": 55,
      "chapterIdx": 25,
      "title": "第9章 如何解决组织中的时间稀缺",
      "level": 2,
      "wordCount": 153,
      "price": -1,
      "paid": 0,
      "isMPChapter": 0,
      "anchors": [],
      "appLink": "weread://reading?bId=853426&chapterUid=55",
      "webLink": "https://weread.qq.com/web/reader/36b321405d05b236bb0ce7d?chapterUid=55"
    },
    {
      "chapterUid": 56,
      "chapterIdx": 26,
      "title": "余闲的重要作用",
      "level": 3,
      "wordCount": 15377,
      "price": -1,
      "paid": 0,
      "isMPChapter": 0,
      "anchors": [
        {
          "title": "余闲的重要作用",
          "anchor": "sigil_toc_id_46",
          "level": 3
        },
        {
          "title": "余闲，不能太多也不能太少",
          "anchor": "sigil_toc_id_47",
          "level": 3
        },
        {
          "title": "4.45倍！火星探测器的教训",
          "anchor": "sigil_toc_id_48",
          "level": 3
        },
        {
          "title": "用余闲对抗救火陷阱",
          "anchor": "sigil_toc_id_49",
          "level": 3
        },
        {
          "title": "亨利·福特的时间管理智慧",
          "anchor": "sigil_toc_id_50",
          "level": 3
        },
        {
          "title": "“红花”日本料理的启示",
          "anchor": "sigil_toc_id_51",
          "level": 3
        },
        {
          "title": "“舍维斯”的餐桌管理经验",
          "anchor": "sigil_toc_id_52",
          "level": 3
        }
      ],
      "appLink": "weread://reading?bId=853426&chapterUid=56",
      "webLink": "https://weread.qq.com/web/reader/36b321405d05b236bb0ce7d?chapterUid=56"
    },
    {
      "chapterUid": 57,
      "chapterIdx": 27,
      "title": "第10章 如何应对日常生活中的稀缺",
      "level": 2,
      "wordCount": 166,
      "price": -1,
      "paid": 0,
      "isMPChapter": 0,
      "anchors": [],
      "appLink": "weread://reading?bId=853426&chapterUid=57",
      "webLink": "https://weread.qq.com/web/reader/36b321405d05b236bb0ce7d?chapterUid=57"
    },
    {
      "chapterUid": 58,
      "chapterIdx": 28,
      "title": "把重要事情拉入“管子”视野中",
      "level": 3,
      "wordCount": 15627,
      "price": -1,
      "paid": 0,
      "isMPChapter": 0,
      "anchors": [
        {
          "title": "让“疏忽”等同“默许”",
          "anchor": "sigil_toc_id_53",
          "level": 3
        },
        {
          "title": "保持警觉",
          "anchor": "sigil_toc_id_54",
          "level": 3
        },
        {
          "title": "找准关联行动时机",
          "anchor": "sigil_toc_id_55",
          "level": 3
        },
        {
          "title": "节约利用带宽",
          "anchor": "sigil_toc_id_56",
          "level": 3
        },
        {
          "title": "在带宽充裕时行动",
          "anchor": "sigil_toc_id_57",
          "level": 3
        },
        {
          "title": "为带宽不足的人提供便利",
          "anchor": "sigil_toc_id_58",
          "level": 3
        },
        {
          "title": "从富足起步",
          "anchor": "sigil_toc_id_59",
          "level": 3
        },
        {
          "title": "以余闲应对突发事件",
          "anchor": "sigil_toc_id_60",
          "level": 3
        }
      ],
      "appLink": "weread://reading?bId=853426&chapterUid=58",
      "webLink": "https://weread.qq.com/web/reader/36b321405d05b236bb0ce7d?chapterUid=58"
    },
    {
      "chapterUid": 59,
      "chapterIdx": 29,
      "title": "结语 规划和管理好“带宽”，稀缺问题就会迎刃而解",
      "level": 1,
      "wordCount": 162,
      "price": -1,
      "paid": 0,
      "isMPChapter": 0,
      "anchors": [],
      "appLink": "weread://reading?bId=853426&chapterUid=59",
      "webLink": "https://weread.qq.com/web/reader/36b321405d05b236bb0ce7d?chapterUid=59"
    },
    {
      "chapterUid": 60,
      "chapterIdx": 30,
      "title": "带宽负担人人都有",
      "level": 2,
      "wordCount": 5111,
      "price": -1,
      "paid": 0,
      "isMPChapter": 0,
      "anchors": [
        {
          "title": "带宽和稀缺心理，解决稀缺问题的关键",
          "anchor": "sigil_toc_id_61",
          "level": 2
        },
        {
          "title": "解决稀缺问题要从富足着手",
          "anchor": "sigil_toc_id_62",
          "level": 2
        }
      ],
      "appLink": "weread://reading?bId=853426&chapterUid=60",
      "webLink": "https://weread.qq.com/web/reader/36b321405d05b236bb0ce7d?chapterUid=60"
    },
    {
      "chapterUid": 61,
      "chapterIdx": 31,
      "title": "译者后记",
      "level": 1,
      "wordCount": 665,
      "price": -1,
      "paid": 0,
      "isMPChapter": 0,
      "anchors": [],
      "appLink": "weread://reading?bId=853426&chapterUid=61",
      "webLink": "https://weread.qq.com/web/reader/36b321405d05b236bb0ce7d?chapterUid=61"
    }
  ],
  "content": [
    {
      "chapterUid": 38,
      "chapterTitle": "资源稀缺换来了专注与回报",
      "items": [
        {
          "type": "highlight",
          "bookmarkId": "853426_38_20495-20575",
          "range": "20495-20575",
          "rangeStart": 20495,
          "rangeEnd": 20575,
          "markText": "稀缺会改变我们看待事物的眼光，让我们做出不同选择。这种现象会让我们变得更有成效；但同时也会让我们为此付出代价：这种“专心致志”会令我们忽略原本很重要的其他事物。",
          "colorStyle": 0,
          "colorLabel": "",
          "createTime": 1727311738,
          "createTimeFormatted": "2024-09-26 08:48:58",
          "chapterUid": 38,
          "appLink": "weread://bestbookmark?bookId=853426&chapterUid=38&rangeStart=20495&rangeEnd=20575",
          "webLink": "https://weread.qq.com/web/reader/36b321405d05b236bb0ce7d?chapterUid=38&rangeStart=20495&rangeEnd=20575"
        }
      ]
    }
  ],
  "bookReviews": [],
  "hotBookmarks": [
    {
      "bookmarkId": "853426_35_6624-6723",
      "chapterUid": 35,
      "range": "6624-6723",
      "markText": "稀缺俘获大脑(scarcity captures the mind)　稀缺造成的后果不仅仅是因为我们会因拥有的太少而感到不悦，而是因为它会改变我们的思维方式，会强行侵入我们的思想之中。",
      "totalCount": 9405,
      "appLink": "weread://bestbookmark?bookId=853426&chapterUid=35&rangeStart=6624&rangeEnd=6723",
      "webLink": "https://weread.qq.com/web/reader/36b321405d05b236bb0ce7d?chapterUid=35&rangeStart=6624&rangeEnd=6723"
    },
    {
      "bookmarkId": "853426_38_20495-20575",
      "chapterUid": 38,
      "range": "20495-20575",
      "markText": "稀缺会改变我们看待事物的眼光，让我们做出不同选择。这种现象会让我们变得更有成效；但同时也会让我们为此付出代价：这种“专心致志”会令我们忽略原本很重要的其他事物。",
      "totalCount": 8768,
      "appLink": "weread://bestbookmark?bookId=853426&chapterUid=38&rangeStart=20495&rangeEnd=20575",
      "webLink": "https://weread.qq.com/web/reader/36b321405d05b236bb0ce7d?chapterUid=38&rangeStart=20495&rangeEnd=20575"
    },
    {
      "bookmarkId": "853426_33_1174-1201",
      "chapterUid": 33,
      "range": "1174-1201",
      "markText": "如果你想要什么，不要等急需的时候才去要，而要提前积累。",
      "totalCount": 7740,
      "appLink": "weread://bestbookmark?bookId=853426&chapterUid=33&rangeStart=1174&rangeEnd=1201",
      "webLink": "https://weread.qq.com/web/reader/36b321405d05b236bb0ce7d?chapterUid=33&rangeStart=1174&rangeEnd=1201"
    },
    {
      "bookmarkId": "853426_38_5638-5724",
      "chapterUid": 38,
      "range": "5638-5724",
      "markText": "无论是有关工作还是娱乐，只要时间有限，我们都会尽量将其利用得淋漓尽致。我们将这种现象称为“专注红利”(focus dividend)，也就是稀缺俘获大脑时所产生的积极成果。",
      "totalCount": 7668,
      "appLink": "weread://bestbookmark?bookId=853426&chapterUid=38&rangeStart=5638&rangeEnd=5724",
      "webLink": "https://weread.qq.com/web/reader/36b321405d05b236bb0ce7d?chapterUid=38&rangeStart=5638&rangeEnd=5724"
    },
    {
      "bookmarkId": "853426_38_11591-11657",
      "chapterUid": 38,
      "range": "11591-11657",
      "markText": "专注具有积极意义：稀缺会迫使我们专注在迫近的重要事情上；管窥则是消极的：稀缺导致我们有了管窥之见，让我们忽略了其他可能更重要的事情。",
      "totalCount": 7582,
      "appLink": "weread://bestbookmark?bookId=853426&chapterUid=38&rangeStart=11591&rangeEnd=11657",
      "webLink": "https://weread.qq.com/web/reader/36b321405d05b236bb0ce7d?chapterUid=38&rangeStart=11591&rangeEnd=11657"
    },
    {
      "bookmarkId": "853426_35_14390-14486",
      "chapterUid": 35,
      "range": "14390-14486",
      "markText": "稀缺会俘获我们的注意力，并带来一点点好处：我们能够在应对迫切需求时，做得更好。但从长远的角度来看，我们的损失更大：我们会忽视其他需要关注的事项，在生活的其他方面变得不那么有成效。",
      "totalCount": 7425,
      "appLink": "weread://bestbookmark?bookId=853426&chapterUid=35&rangeStart=14390&rangeEnd=14486",
      "webLink": "https://weread.qq.com/web/reader/36b321405d05b236bb0ce7d?chapterUid=35&rangeStart=14390&rangeEnd=14486"
    },
    {
      "bookmarkId": "853426_35_12806-12898",
      "chapterUid": 35,
      "range": "12806-12898",
      "markText": "带宽(bandwidth)　就是心智的容量，包括两种能力，分别为认知能力和执行控制力。稀缺会降低所有这些带宽的容量，致使我们缺乏洞察力和前瞻性，还会减弱我们的执行控制力。",
      "totalCount": 7088,
      "appLink": "weread://bestbookmark?bookId=853426&chapterUid=35&rangeStart=12806&rangeEnd=12898",
      "webLink": "https://weread.qq.com/web/reader/36b321405d05b236bb0ce7d?chapterUid=35&rangeStart=12806&rangeEnd=12898"
    },
    {
      "bookmarkId": "853426_38_3127-3162",
      "chapterUid": 38,
      "range": "3127-3162",
      "markText": "一旦时间不够用的现实变得无法逃避，我们就会开始集中精力。",
      "totalCount": 6300,
      "appLink": "weread://bestbookmark?bookId=853426&chapterUid=38&rangeStart=3127&rangeEnd=3162",
      "webLink": "https://weread.qq.com/web/reader/36b321405d05b236bb0ce7d?chapterUid=38&rangeStart=3127&rangeEnd=3162"
    },
    {
      "bookmarkId": "853426_38_8864-8956",
      "chapterUid": 38,
      "range": "8864-8956",
      "markText": "我们不能通过胳肢自己来取乐，同样，也很难以提高工作绩效为目的，用假装有个截止日期的方式来自我欺骗。空想出来的截止日期不过是一个空想而已，它永远也不会像真正的截止日期那样俘获我们的大脑。",
      "totalCount": 5724,
      "appLink": "weread://bestbookmark?bookId=853426&chapterUid=38&rangeStart=8864&rangeEnd=8956",
      "webLink": "https://weread.qq.com/web/reader/36b321405d05b236bb0ce7d?chapterUid=38&rangeStart=8864&rangeEnd=8956"
    },
    {
      "bookmarkId": "853426_34_534-610",
      "chapterUid": 34,
      "range": "534-610",
      "markText": "阅读一本书并不是要把书中的每一行的每个字都认一遍，而是较真地弄明白作者的意思，并理解作者的思想，才能进一步真正掌握一本书的观点、视角以及可能的现实应用。",
      "totalCount": 5512,
      "appLink": "weread://bestbookmark?bookId=853426&chapterUid=34&rangeStart=534&rangeEnd=610",
      "webLink": "https://weread.qq.com/web/reader/36b321405d05b236bb0ce7d?chapterUid=34&rangeStart=534&rangeEnd=610"
    },
    {
      "bookmarkId": "853426_38_1806-1841",
      "chapterUid": 38,
      "range": "1806-1841",
      "markText": "稀缺，会迫使人做出选择。所有抽象的事物都会变得具体起来。",
      "totalCount": 5280,
      "appLink": "weread://bestbookmark?bookId=853426&chapterUid=38&rangeStart=1806&rangeEnd=1841",
      "webLink": "https://weread.qq.com/web/reader/36b321405d05b236bb0ce7d?chapterUid=38&rangeStart=1806&rangeEnd=1841"
    },
    {
      "bookmarkId": "853426_40_8416-8458",
      "chapterUid": 40,
      "range": "8416-8458",
      "markText": "稀缺会直接减少带宽——不是减少某人与生俱来的带宽容量，而是减少其当下能用得上的容量。",
      "totalCount": 5094,
      "appLink": "weread://bestbookmark?bookId=853426&chapterUid=40&rangeStart=8416&rangeEnd=8458",
      "webLink": "https://weread.qq.com/web/reader/36b321405d05b236bb0ce7d?chapterUid=40&rangeStart=8416&rangeEnd=8458"
    },
    {
      "bookmarkId": "853426_35_12443-12518",
      "chapterUid": 35,
      "range": "12443-12518",
      "markText": "稀缺心态(scarcity mindset)　稀缺是一种心态。当它俘获我们的注意力时，就会改变我们的思维方式，影响我们的决策和行为方式。",
      "totalCount": 4768,
      "appLink": "weread://bestbookmark?bookId=853426&chapterUid=35&rangeStart=12443&rangeEnd=12518",
      "webLink": "https://weread.qq.com/web/reader/36b321405d05b236bb0ce7d?chapterUid=35&rangeStart=12443&rangeEnd=12518"
    },
    {
      "bookmarkId": "853426_38_10886-10937",
      "chapterUid": 38,
      "range": "10886-10937",
      "markText": "管窥(tunneling)　专注于某一事物就意味着我们会忽略其他事物，也叫“隧道视野”。",
      "totalCount": 4662,
      "appLink": "weread://bestbookmark?bookId=853426&chapterUid=38&rangeStart=10886&rangeEnd=10937",
      "webLink": "https://weread.qq.com/web/reader/36b321405d05b236bb0ce7d?chapterUid=38&rangeStart=10886&rangeEnd=10937"
    },
    {
      "bookmarkId": "853426_35_3458-3475",
      "chapterUid": 35,
      "range": "3458-3475",
      "markText": "稀缺，是“拥有”少于“需要”的感觉",
      "totalCount": 4590,
      "appLink": "weread://bestbookmark?bookId=853426&chapterUid=35&rangeStart=3458&rangeEnd=3475",
      "webLink": "https://weread.qq.com/web/reader/36b321405d05b236bb0ce7d?chapterUid=35&rangeStart=3458&rangeEnd=3475"
    },
    {
      "bookmarkId": "853426_45_16731-16777",
      "chapterUid": 45,
      "range": "16731-16777",
      "markText": "因为专注，所以拥有专业技能；因为专业，所以有了管窥之见；因为管窥，所以产生了一系列负面后果。",
      "totalCount": 4560,
      "appLink": "weread://bestbookmark?bookId=853426&chapterUid=45&rangeStart=16731&rangeEnd=16777",
      "webLink": "https://weread.qq.com/web/reader/36b321405d05b236bb0ce7d?chapterUid=45&rangeStart=16731&rangeEnd=16777"
    },
    {
      "bookmarkId": "853426_38_5296-5342",
      "chapterUid": 38,
      "range": "5296-5342",
      "markText": "截止日期是一种很有效的手段，之所以这么说，是因为产生了时间稀缺，而它可以让人集中精力去做事。",
      "totalCount": 4216,
      "appLink": "weread://bestbookmark?bookId=853426&chapterUid=38&rangeStart=5296&rangeEnd=5342",
      "webLink": "https://weread.qq.com/web/reader/36b321405d05b236bb0ce7d?chapterUid=38&rangeStart=5296&rangeEnd=5342"
    },
    {
      "bookmarkId": "853426_47_5817-5917",
      "chapterUid": 47,
      "range": "5817-5917",
      "markText": "当今天的资源，无论是时间还是金钱，能在当下为你带来比未来更大的利益时，借用就是行得通的做法。而当我们有了管窥之见时，借用就会超越得失均衡的限度。当面临稀缺状况时，我们的借用，从长期来看通常是不合理的。",
      "totalCount": 4185,
      "appLink": "weread://bestbookmark?bookId=853426&chapterUid=47&rangeStart=5817&rangeEnd=5917",
      "webLink": "https://weread.qq.com/web/reader/36b321405d05b236bb0ce7d?chapterUid=47&rangeStart=5817&rangeEnd=5917"
    },
    {
      "bookmarkId": "853426_35_9681-9704",
      "chapterUid": 35,
      "range": "9681-9704",
      "markText": "孤独者非常善于记住与他人互动等社交内容的细节。",
      "totalCount": 3752,
      "appLink": "weread://bestbookmark?bookId=853426&chapterUid=35&rangeStart=9681&rangeEnd=9704",
      "webLink": "https://weread.qq.com/web/reader/36b321405d05b236bb0ce7d?chapterUid=35&rangeStart=9681&rangeEnd=9704"
    },
    {
      "bookmarkId": "853426_43_7844-7893",
      "chapterUid": 43,
      "range": "7844-7893",
      "markText": "经济学家们称这种现象为边际效用递减，即你拥有的越多，对你而言，每一样额外增加的物品的价值就会越低。",
      "totalCount": 3392,
      "appLink": "weread://bestbookmark?bookId=853426&chapterUid=43&rangeStart=7844&rangeEnd=7893",
      "webLink": "https://weread.qq.com/web/reader/36b321405d05b236bb0ce7d?chapterUid=43&rangeStart=7844&rangeEnd=7893"
    }
  ],
  "readProgress": {
    "chapterUid": 38,
    "chapterOffset": 336,
    "progress": 0,
    "updateTime": 1727330023,
    "recordReadingTime": 0,
    "finishTime": ""
  }
}