{
  "meta": {
    "bookId": "CB_D4c8by8bZCnZ70L71E3uT1z7",
    "title": "Liquid Times: Living in an Age of Uncertainty",
    "author": "Zygmunt Bauman",
    "translator": "",
    "cover": "https://res.weread.qq.com/wrepub/CB_DRRFJ3FFq6ry6w66xG7s61jz_parsecover",
    "intro": "",
    "category": "",
    "publisher": "Polity",
    "publishTime": "",
    "isbn": "",
    "wordCount": 0,
    "newRating": 0,
    "newRatingCount": 0,
    "newRatingDetail": {
      "good": 0,
      "fair": 0,
      "poor": 0,
      "recent": 0,
      "deepV": 0,
      "myRating": "",
      "title": "待评分"
    },
    "appLink": "weread://reading?bId=CB_D4c8by8bZCnZ70L71E3uT1z7",
    "webLink": "https://weread.qq.com/web/reader/1dc427d3643425f44346338627938625a436e5a37304c373145337554317a372d8",
    "lastSync": "2026-05-21T11:47:10Z",
    "readingProgress": "19%",
    "readingTime": "0分钟",
    "finishedDate": "",
    "noteCount": 10,
    "reviewCount": 2,
    "bookmarkCount": 0,
    "contentHash": "2b67a6af6f750f36744026210cb84bb71b2734b279e1980fcc157c5281b73445"
  },
  "chapters": [
    {
      "chapterUid": 1,
      "chapterIdx": 1,
      "title": "Cover",
      "level": 1,
      "wordCount": 12,
      "price": 0,
      "paid": 0,
      "isMPChapter": 0,
      "anchors": [],
      "appLink": "weread://reading?bId=CB_D4c8by8bZCnZ70L71E3uT1z7&chapterUid=1",
      "webLink": "https://weread.qq.com/web/reader/1dc427d3643425f44346338627938625a436e5a37304c373145337554317a372d8?chapterUid=1"
    },
    {
      "chapterUid": 2,
      "chapterIdx": 2,
      "title": "HalfTitle",
      "level": 1,
      "wordCount": 23,
      "price": 0,
      "paid": 0,
      "isMPChapter": 0,
      "anchors": [],
      "appLink": "weread://reading?bId=CB_D4c8by8bZCnZ70L71E3uT1z7&chapterUid=2",
      "webLink": "https://weread.qq.com/web/reader/1dc427d3643425f44346338627938625a436e5a37304c373145337554317a372d8?chapterUid=2"
    },
    {
      "chapterUid": 3,
      "chapterIdx": 3,
      "title": "Title",
      "level": 1,
      "wordCount": 68,
      "price": 0,
      "paid": 0,
      "isMPChapter": 0,
      "anchors": [],
      "appLink": "weread://reading?bId=CB_D4c8by8bZCnZ70L71E3uT1z7&chapterUid=3",
      "webLink": "https://weread.qq.com/web/reader/1dc427d3643425f44346338627938625a436e5a37304c373145337554317a372d8?chapterUid=3"
    },
    {
      "chapterUid": 4,
      "chapterIdx": 4,
      "title": "Copyright",
      "level": 1,
      "wordCount": 983,
      "price": 0,
      "paid": 0,
      "isMPChapter": 0,
      "anchors": [],
      "appLink": "weread://reading?bId=CB_D4c8by8bZCnZ70L71E3uT1z7&chapterUid=4",
      "webLink": "https://weread.qq.com/web/reader/1dc427d3643425f44346338627938625a436e5a37304c373145337554317a372d8?chapterUid=4"
    },
    {
      "chapterUid": 5,
      "chapterIdx": 5,
      "title": "Contents",
      "level": 1,
      "wordCount": 210,
      "price": 0,
      "paid": 0,
      "isMPChapter": 0,
      "anchors": [],
      "appLink": "weread://reading?bId=CB_D4c8by8bZCnZ70L71E3uT1z7&chapterUid=5",
      "webLink": "https://weread.qq.com/web/reader/1dc427d3643425f44346338627938625a436e5a37304c373145337554317a372d8?chapterUid=5"
    },
    {
      "chapterUid": 6,
      "chapterIdx": 6,
      "title": "Introduction: Bravely into the Hotbed of Uncertainties",
      "level": 1,
      "wordCount": 6151,
      "price": 0,
      "paid": 0,
      "isMPChapter": 0,
      "anchors": [],
      "appLink": "weread://reading?bId=CB_D4c8by8bZCnZ70L71E3uT1z7&chapterUid=6",
      "webLink": "https://weread.qq.com/web/reader/1dc427d3643425f44346338627938625a436e5a37304c373145337554317a372d8?chapterUid=6"
    },
    {
      "chapterUid": 7,
      "chapterIdx": 7,
      "title": "1: Liquid Modern Life and its Fears",
      "level": 1,
      "wordCount": 35101,
      "price": 0,
      "paid": 0,
      "isMPChapter": 0,
      "anchors": [],
      "appLink": "weread://reading?bId=CB_D4c8by8bZCnZ70L71E3uT1z7&chapterUid=7",
      "webLink": "https://weread.qq.com/web/reader/1dc427d3643425f44346338627938625a436e5a37304c373145337554317a372d8?chapterUid=7"
    },
    {
      "chapterUid": 8,
      "chapterIdx": 8,
      "title": "2: Humanity on the Move",
      "level": 1,
      "wordCount": 43123,
      "price": 0,
      "paid": 0,
      "isMPChapter": 0,
      "anchors": [],
      "appLink": "weread://reading?bId=CB_D4c8by8bZCnZ70L71E3uT1z7&chapterUid=8",
      "webLink": "https://weread.qq.com/web/reader/1dc427d3643425f44346338627938625a436e5a37304c373145337554317a372d8?chapterUid=8"
    },
    {
      "chapterUid": 9,
      "chapterIdx": 9,
      "title": "3: State,Democracy and the Management of Fears",
      "level": 1,
      "wordCount": 25707,
      "price": 0,
      "paid": 0,
      "isMPChapter": 0,
      "anchors": [],
      "appLink": "weread://reading?bId=CB_D4c8by8bZCnZ70L71E3uT1z7&chapterUid=9",
      "webLink": "https://weread.qq.com/web/reader/1dc427d3643425f44346338627938625a436e5a37304c373145337554317a372d8?chapterUid=9"
    },
    {
      "chapterUid": 10,
      "chapterIdx": 10,
      "title": "4: Out of Touch Together",
      "level": 1,
      "wordCount": 35588,
      "price": 0,
      "paid": 0,
      "isMPChapter": 0,
      "anchors": [],
      "appLink": "weread://reading?bId=CB_D4c8by8bZCnZ70L71E3uT1z7&chapterUid=10",
      "webLink": "https://weread.qq.com/web/reader/1dc427d3643425f44346338627938625a436e5a37304c373145337554317a372d8?chapterUid=10"
    },
    {
      "chapterUid": 11,
      "chapterIdx": 11,
      "title": "5: Utopia in the Age of Uncertainty",
      "level": 1,
      "wordCount": 25866,
      "price": 0,
      "paid": 0,
      "isMPChapter": 0,
      "anchors": [],
      "appLink": "weread://reading?bId=CB_D4c8by8bZCnZ70L71E3uT1z7&chapterUid=11",
      "webLink": "https://weread.qq.com/web/reader/1dc427d3643425f44346338627938625a436e5a37304c373145337554317a372d8?chapterUid=11"
    },
    {
      "chapterUid": 12,
      "chapterIdx": 12,
      "title": "Notes",
      "level": 1,
      "wordCount": 6844,
      "price": 0,
      "paid": 0,
      "isMPChapter": 0,
      "anchors": [],
      "appLink": "weread://reading?bId=CB_D4c8by8bZCnZ70L71E3uT1z7&chapterUid=12",
      "webLink": "https://weread.qq.com/web/reader/1dc427d3643425f44346338627938625a436e5a37304c373145337554317a372d8?chapterUid=12"
    }
  ],
  "content": [
    {
      "chapterUid": 6,
      "chapterTitle": "Introduction: Bravely into the Hotbed of Uncertainties",
      "items": [
        {
          "type": "highlight",
          "bookmarkId": "CB_D4c8by8bZCnZ70L71E3uT1z7_6_1428-1862",
          "range": "1428-1862",
          "rangeStart": 1428,
          "rangeEnd": 1862,
          "markText": "First of all, the passage from the ‘solid’ to a ‘liquid’ phase of modernity: that is, into a condition in which social forms (structures that limit individual choices, institutions that guard repetitions of routines, patterns of acceptable behaviour) can no longer (and are not expected) to keep their shape for long, because they decompose and melt faster than the time it takes to cast them, and once they are cast for them to set. ",
          "colorStyle": 0,
          "colorLabel": "",
          "createTime": 1764852485,
          "createTimeFormatted": "2025-12-04 20:48:05",
          "chapterUid": 6,
          "appLink": "weread://bestbookmark?bookId=CB_D4c8by8bZCnZ70L71E3uT1z7&chapterUid=6&rangeStart=1428&rangeEnd=1862",
          "webLink": "https://weread.qq.com/web/reader/1dc427d3643425f44346338627938625a436e5a37304c373145337554317a372d8?chapterUid=6&rangeStart=1428&rangeEnd=1862"
        },
        {
          "type": "highlight",
          "bookmarkId": "CB_D4c8by8bZCnZ70L71E3uT1z7_6_2610-2842",
          "range": "2610-2842",
          "rangeStart": 2610,
          "rangeEnd": 2842,
          "markText": "Second, the separation and pending divorce of power and politics, the couple that since the emergence of the modern state and until quite recently was expected to share their joint nation-state household ‘till death did them part’. ",
          "colorStyle": 0,
          "colorLabel": "",
          "createTime": 1764852441,
          "createTimeFormatted": "2025-12-04 20:47:21",
          "chapterUid": 6,
          "appLink": "weread://bestbookmark?bookId=CB_D4c8by8bZCnZ70L71E3uT1z7&chapterUid=6&rangeStart=2610&rangeEnd=2842",
          "webLink": "https://weread.qq.com/web/reader/1dc427d3643425f44346338627938625a436e5a37304c373145337554317a372d8?chapterUid=6&rangeStart=2610&rangeEnd=2842"
        },
        {
          "type": "highlight",
          "bookmarkId": "CB_D4c8by8bZCnZ70L71E3uT1z7_6_4570-4968",
          "range": "4570-4968",
          "rangeStart": 4570,
          "rangeEnd": 4968,
          "markText": "Third, the gradual yet consistent withdrawal or curtailing of communal, state-endorsed insurance against individual failure and ill fortune deprives collective action of much of its past attraction and saps the social foundations of social solidarity; ‘community’, as a way of referring to the totality of the population inhabiting the sovereign territory of the state, sounds increasingly hollow. ",
          "colorStyle": 0,
          "colorLabel": "",
          "createTime": 1764852416,
          "createTimeFormatted": "2025-12-04 20:46:56",
          "chapterUid": 6,
          "appLink": "weread://bestbookmark?bookId=CB_D4c8by8bZCnZ70L71E3uT1z7&chapterUid=6&rangeStart=4570&rangeEnd=4968",
          "webLink": "https://weread.qq.com/web/reader/1dc427d3643425f44346338627938625a436e5a37304c373145337554317a372d8?chapterUid=6&rangeStart=4570&rangeEnd=4968"
        },
        {
          "type": "highlight",
          "bookmarkId": "CB_D4c8by8bZCnZ70L71E3uT1z7_6_6315-6872",
          "range": "6315-6872",
          "rangeStart": 6315,
          "rangeEnd": 6872,
          "markText": "Fourth, the collapse of long-term thinking, planning and acting, and the disappearance or weakening of social structures in which thinking, planning and acting could be inscribed for a long time to come, leads to a splicing of both political history and individual lives into a series of short-term projects and episodes which are in principle inﬁnite, and do not combine into the kinds of sequences to which concepts like ‘development’, ‘maturation’, ‘career’ or ‘progress’ (all suggesting a preordained order of succession) could be meaningfully applied. ",
          "colorStyle": 0,
          "colorLabel": "",
          "createTime": 1764852392,
          "createTimeFormatted": "2025-12-04 20:46:32",
          "chapterUid": 6,
          "appLink": "weread://bestbookmark?bookId=CB_D4c8by8bZCnZ70L71E3uT1z7&chapterUid=6&rangeStart=6315&rangeEnd=6872",
          "webLink": "https://weread.qq.com/web/reader/1dc427d3643425f44346338627938625a436e5a37304c373145337554317a372d8?chapterUid=6&rangeStart=6315&rangeEnd=6872"
        },
        {
          "type": "highlight",
          "bookmarkId": "CB_D4c8by8bZCnZ70L71E3uT1z7_6_8135-8419",
          "range": "8135-8419",
          "rangeStart": 8135,
          "rangeEnd": 8419,
          "markText": "Fifth, the responsibility for resolving the quandaries generated by vexingly volatile and constantly changing circumstances is shifted onto the shoulders of individuals – who are now expected to be ‘free choosers’ and to bear in full the consequences of their choices.﻿",
          "colorStyle": 0,
          "colorLabel": "",
          "createTime": 1764852312,
          "createTimeFormatted": "2025-12-04 20:45:12",
          "chapterUid": 6,
          "appLink": "weread://bestbookmark?bookId=CB_D4c8by8bZCnZ70L71E3uT1z7&chapterUid=6&rangeStart=8135&rangeEnd=8419",
          "webLink": "https://weread.qq.com/web/reader/1dc427d3643425f44346338627938625a436e5a37304c373145337554317a372d8?chapterUid=6&rangeStart=8135&rangeEnd=8419"
        },
        {
          "type": "highlight",
          "bookmarkId": "CB_D4c8by8bZCnZ70L71E3uT1z7_6_9282-9363",
          "range": "9282-9363",
          "rangeStart": 9282,
          "rangeEnd": 9363,
          "markText": "第五，由于形势变化剧烈且持续不断，由此产生的种种困境所带来的责任被转嫁到了个人身上——现在人们期望个人能够成为“自由的选择者”，并必须完全承担自己所做选择的后果。",
          "colorStyle": 0,
          "colorLabel": "",
          "createTime": 1764852296,
          "createTimeFormatted": "2025-12-04 20:44:56",
          "chapterUid": 6,
          "appLink": "weread://bestbookmark?bookId=CB_D4c8by8bZCnZ70L71E3uT1z7&chapterUid=6&rangeStart=9282&rangeEnd=9363",
          "webLink": "https://weread.qq.com/web/reader/1dc427d3643425f44346338627938625a436e5a37304c373145337554317a372d8?chapterUid=6&rangeStart=9282&rangeEnd=9363"
        },
        {
          "type": "highlight",
          "bookmarkId": "CB_D4c8by8bZCnZ70L71E3uT1z7_6_7712-7794",
          "range": "7712-7794",
          "rangeStart": 7712,
          "rangeEnd": 7794,
          "markText": "第四，长期思考、规划与行动能力的衰退，以及那些原本能够支撑这种长期思考、规划与行动的社会结构的瓦解或削弱，导致政治历史与个人生活都被切割成一系列短期性的事件与片段。",
          "colorStyle": 1,
          "colorLabel": "",
          "createTime": 1764852232,
          "createTimeFormatted": "2025-12-04 20:43:52",
          "chapterUid": 6,
          "appLink": "weread://bestbookmark?bookId=CB_D4c8by8bZCnZ70L71E3uT1z7&chapterUid=6&rangeStart=7712&rangeEnd=7794",
          "webLink": "https://weread.qq.com/web/reader/1dc427d3643425f44346338627938625a436e5a37304c373145337554317a372d8?chapterUid=6&rangeStart=7712&rangeEnd=7794"
        },
        {
          "type": "highlight",
          "bookmarkId": "CB_D4c8by8bZCnZ70L71E3uT1z7_6_5890-6019",
          "range": "5890-6019",
          "rangeStart": 5890,
          "rangeEnd": 6019,
          "markText": "第三，国家逐步但持续地撤销或削减那些为应对个人遭遇失败或不幸而提供的、由政府支持的保险制度，这使得集体行动失去了昔日的吸引力，同时也削弱了社会团结的社会基础；“社区”这一概念，作为指代生活在国家主权领土范围内的全体居民的方式，如今听起来已经越来越空洞无物了。",
          "colorStyle": 1,
          "colorLabel": "",
          "createTime": 1764852217,
          "createTimeFormatted": "2025-12-04 20:43:37",
          "chapterUid": 6,
          "appLink": "weread://bestbookmark?bookId=CB_D4c8by8bZCnZ70L71E3uT1z7&chapterUid=6&rangeStart=5890&rangeEnd=6019",
          "webLink": "https://weread.qq.com/web/reader/1dc427d3643425f44346338627938625a436e5a37304c373145337554317a372d8?chapterUid=6&rangeStart=5890&rangeEnd=6019"
        },
        {
          "type": "highlight",
          "bookmarkId": "CB_D4c8by8bZCnZ70L71E3uT1z7_6_4106-4175",
          "range": "4106-4175",
          "rangeStart": 4106,
          "rangeEnd": 4175,
          "markText": "其次，权力与政治之间的分离以及正在进行的离婚进程——自从现代国家诞生以来，人们一直认为这种权力与政治的结合关系会“持续到死亡将他们分开”。",
          "colorStyle": 1,
          "colorLabel": "",
          "createTime": 1764852190,
          "createTimeFormatted": "2025-12-04 20:43:10",
          "chapterUid": 6,
          "appLink": "weread://bestbookmark?bookId=CB_D4c8by8bZCnZ70L71E3uT1z7&chapterUid=6&rangeStart=4106&rangeEnd=4175",
          "webLink": "https://weread.qq.com/web/reader/1dc427d3643425f44346338627938625a436e5a37304c373145337554317a372d8?chapterUid=6&rangeStart=4106&rangeEnd=4175"
        },
        {
          "type": "highlight",
          "bookmarkId": "CB_D4c8by8bZCnZ70L71E3uT1z7_6_2313-2449",
          "range": "2313-2449",
          "rangeStart": 2313,
          "rangeEnd": 2449,
          "markText": "首先，现代性从“固态”阶段转变为“液态”阶段：也就是说，社会形态（那些限制个人选择的制度、那些维护日常行为模式重复性的机制、那些规定何种行为是可接受的规范）不再能够长期保持原有的形态，也不被期望能够长期保持这种形态，因为这些社会形态的分解与瓦解速度远远快于形成它们的过程。",
          "colorStyle": 1,
          "colorLabel": "",
          "createTime": 1764852176,
          "createTimeFormatted": "2025-12-04 20:42:56",
          "chapterUid": 6,
          "appLink": "weread://bestbookmark?bookId=CB_D4c8by8bZCnZ70L71E3uT1z7&chapterUid=6&rangeStart=2313&rangeEnd=2449",
          "webLink": "https://weread.qq.com/web/reader/1dc427d3643425f44346338627938625a436e5a37304c373145337554317a372d8?chapterUid=6&rangeStart=2313&rangeEnd=2449"
        },
        {
          "type": "review",
          "reviewId": "32618646_859dA6zVb",
          "range": "10642-10946",
          "chapterName": "Introduction: Bravely into the Hotbed of Uncertainties",
          "content": "1.现代性正从固体阶段向流动阶段过渡；\n2.权利与政治的亲密关系即将解体；\n3.社群的以及由国家支撑的抵御个体失败和厄运的保障，正在逐渐地、持续不断的收缩以及缩减，这种现象削弱了这种保障从前所具有的种种吸引力，同时也破坏了社会连带的社会基础；\n4.长期性的思考、计划及行动日渐崩溃，同时，允许这些活动长期存在的社会结构也在消失或削弱，这一现象导致政治史的断裂，也使得个体的生命历程断裂为一系列的短期的计划和一段段的小插曲；\n5.环境总是如此变化多端，没有定式，但解决由此而产生的各种困境之责则落到了个体的头上——个体被期望成为“自由的抉择者”，而且应该为自己得选择付出全责。\n可以概括为，社会结构从提供稳定框架的“固态”溶解为充满不确定的“液态”，曾经由集体承担的风险与责任，如今几乎全部转移至个体身上。 其结果是个体必须在缺乏长期导航图的环境中，独自进行短期决策并承担其全部重量。",
          "abstract": "现在是时候思考：这些变化究竟如何改变了男女在人生追求中所面临的种种挑战，进而间接地影响了他们的生活方式了。这本书正是试图探讨这个问题——提出问题，但不试图给出答案，更不会假装能够提供确定的答案。因为作者认为，任何答案都可能具有绝对性、显得为时过早，或者容易产生误导。毕竟，上述这些变化所带来的最终结果，就是人们必须采取行动、制定计划、计算这些行动可能带来的收益与损失，并在充满不确定性的环境中评估这些行动的实际效果。作者所能做的、也认为自己有权利去做的，就是探究这种不确定性的根源——或许还能揭示出那些阻碍人们理解这些现象的障碍，从而帮助我们（无论是个人还是集体）更好地应对任何试图控制这些现象所带来的挑战。",
          "star": -1,
          "createTime": 1764852563,
          "createTimeFormatted": "2025-12-04 20:49:23",
          "isFinish": false,
          "chapterUid": 6
        }
      ]
    },
    {
      "chapterUid": 3,
      "chapterTitle": "Title",
      "items": [
        {
          "type": "review",
          "reviewId": "32618646_859rImrXR",
          "range": "665-671",
          "chapterName": "Title",
          "content": "/ˈlɪkwɪd/\nn. 液体,液态物;液态\nn. 【语】流音(指/l/或/r/)\na. 液体的,流质的;液态的,流淌的;熔融的\na. 清澈的;明亮的\na. (声音等)清脆的,柔美的;(语言等)流畅的\na. 【语】流音的\na. (动作)优美舒展的\na. 不固定的;不稳定的\na. 易变为现金的\na. 拥有现金(或流动资产)的\na. (市场)交易活跃的",
          "abstract": "Liquid",
          "star": -1,
          "createTime": 1764865511,
          "createTimeFormatted": "2025-12-05 00:25:11",
          "isFinish": false,
          "chapterUid": 3
        }
      ]
    }
  ],
  "bookReviews": [],
  "hotBookmarks": [],
  "readProgress": {
    "chapterUid": 6,
    "chapterOffset": 9979,
    "progress": 19,
    "updateTime": 1770368192,
    "recordReadingTime": 0,
    "finishTime": ""
  }
}