{
  "meta": {
    "bookId": "CB_CKd9vz9vx6ti71y71E21O0YE",
    "title": "丞相世家：南宋四明史氏家族研究",
    "author": "刘广丰",
    "translator": "",
    "cover": "https://res.weread.qq.com/wrepub/CB_CKd9vz9vx6ti71y71E21O0YE_parsecover",
    "intro": "",
    "category": "",
    "publisher": "中华书局",
    "publishTime": "",
    "isbn": "",
    "wordCount": 0,
    "newRating": 0,
    "newRatingCount": 0,
    "newRatingDetail": {
      "good": 0,
      "fair": 0,
      "poor": 0,
      "recent": 0,
      "deepV": 0,
      "myRating": "",
      "title": "待评分"
    },
    "appLink": "weread://reading?bId=CB_CKd9vz9vx6ti71y71E21O0YE",
    "webLink": "https://weread.qq.com/web/reader/87542583643425f434b6439767a39767836746937317937314532314f3059455b6",
    "lastSync": "2026-05-21T11:45:49Z",
    "readingProgress": "0%",
    "readingTime": "0分钟",
    "finishedDate": "",
    "noteCount": 0,
    "reviewCount": 1,
    "bookmarkCount": 0,
    "contentHash": "1117cfdd731bcbbbff1d63c13bf3c60602e3503e48e55631d393ff4a9920f588"
  },
  "chapters": [
    {
      "chapterUid": 1,
      "chapterIdx": 1,
      "title": "序",
      "level": 1,
      "wordCount": 1965,
      "price": 0,
      "paid": 0,
      "isMPChapter": 0,
      "anchors": [],
      "appLink": "weread://reading?bId=CB_CKd9vz9vx6ti71y71E21O0YE&chapterUid=1",
      "webLink": "https://weread.qq.com/web/reader/87542583643425f434b6439767a39767836746937317937314532314f3059455b6?chapterUid=1"
    },
    {
      "chapterUid": 2,
      "chapterIdx": 2,
      "title": "悼念我的恩师刘子健教授(1)",
      "level": 1,
      "wordCount": 1629,
      "price": 0,
      "paid": 0,
      "isMPChapter": 0,
      "anchors": [],
      "appLink": "weread://reading?bId=CB_CKd9vz9vx6ti71y71E21O0YE&chapterUid=2",
      "webLink": "https://weread.qq.com/web/reader/87542583643425f434b6439767a39767836746937317937314532314f3059455b6?chapterUid=2"
    },
    {
      "chapterUid": 3,
      "chapterIdx": 3,
      "title": "自 序",
      "level": 1,
      "wordCount": 5699,
      "price": 0,
      "paid": 0,
      "isMPChapter": 0,
      "anchors": [],
      "appLink": "weread://reading?bId=CB_CKd9vz9vx6ti71y71E21O0YE&chapterUid=3",
      "webLink": "https://weread.qq.com/web/reader/87542583643425f434b6439767a39767836746937317937314532314f3059455b6?chapterUid=3"
    },
    {
      "chapterUid": 4,
      "chapterIdx": 4,
      "title": "目次",
      "level": 1,
      "wordCount": 169,
      "price": 0,
      "paid": 0,
      "isMPChapter": 0,
      "anchors": [],
      "appLink": "weread://reading?bId=CB_CKd9vz9vx6ti71y71E21O0YE&chapterUid=4",
      "webLink": "https://weread.qq.com/web/reader/87542583643425f434b6439767a39767836746937317937314532314f3059455b6?chapterUid=4"
    },
    {
      "chapterUid": 5,
      "chapterIdx": 5,
      "title": "绪 论 中央地方",
      "level": 1,
      "wordCount": 12648,
      "price": 0,
      "paid": 0,
      "isMPChapter": 0,
      "anchors": [],
      "appLink": "weread://reading?bId=CB_CKd9vz9vx6ti71y71E21O0YE&chapterUid=5",
      "webLink": "https://weread.qq.com/web/reader/87542583643425f434b6439767a39767836746937317937314532314f3059455b6?chapterUid=5"
    },
    {
      "chapterUid": 6,
      "chapterIdx": 6,
      "title": "第一章 四明故事",
      "level": 1,
      "wordCount": 89,
      "price": 0,
      "paid": 0,
      "isMPChapter": 0,
      "anchors": [],
      "appLink": "weread://reading?bId=CB_CKd9vz9vx6ti71y71E21O0YE&chapterUid=6",
      "webLink": "https://weread.qq.com/web/reader/87542583643425f434b6439767a39767836746937317937314532314f3059455b6?chapterUid=6"
    },
    {
      "chapterUid": 7,
      "chapterIdx": 7,
      "title": "一、入仕之途",
      "level": 2,
      "wordCount": 2937,
      "price": 0,
      "paid": 0,
      "isMPChapter": 0,
      "anchors": [],
      "appLink": "weread://reading?bId=CB_CKd9vz9vx6ti71y71E21O0YE&chapterUid=7",
      "webLink": "https://weread.qq.com/web/reader/87542583643425f434b6439767a39767836746937317937314532314f3059455b6?chapterUid=7"
    },
    {
      "chapterUid": 8,
      "chapterIdx": 8,
      "title": "二、世易时移",
      "level": 2,
      "wordCount": 2465,
      "price": 0,
      "paid": 0,
      "isMPChapter": 0,
      "anchors": [],
      "appLink": "weread://reading?bId=CB_CKd9vz9vx6ti71y71E21O0YE&chapterUid=8",
      "webLink": "https://weread.qq.com/web/reader/87542583643425f434b6439767a39767836746937317937314532314f3059455b6?chapterUid=8"
    },
    {
      "chapterUid": 9,
      "chapterIdx": 9,
      "title": "三、教育与职任",
      "level": 2,
      "wordCount": 7432,
      "price": 0,
      "paid": 0,
      "isMPChapter": 0,
      "anchors": [],
      "appLink": "weread://reading?bId=CB_CKd9vz9vx6ti71y71E21O0YE&chapterUid=9",
      "webLink": "https://weread.qq.com/web/reader/87542583643425f434b6439767a39767836746937317937314532314f3059455b6?chapterUid=9"
    },
    {
      "chapterUid": 10,
      "chapterIdx": 10,
      "title": "第二章 考镜源流",
      "level": 1,
      "wordCount": 280,
      "price": 0,
      "paid": 0,
      "isMPChapter": 0,
      "anchors": [],
      "appLink": "weread://reading?bId=CB_CKd9vz9vx6ti71y71E21O0YE&chapterUid=10",
      "webLink": "https://weread.qq.com/web/reader/87542583643425f434b6439767a39767836746937317937314532314f3059455b6?chapterUid=10"
    },
    {
      "chapterUid": 11,
      "chapterIdx": 11,
      "title": "一、迁徙",
      "level": 2,
      "wordCount": 1930,
      "price": 0,
      "paid": 0,
      "isMPChapter": 0,
      "anchors": [],
      "appLink": "weread://reading?bId=CB_CKd9vz9vx6ti71y71E21O0YE&chapterUid=11",
      "webLink": "https://weread.qq.com/web/reader/87542583643425f434b6439767a39767836746937317937314532314f3059455b6?chapterUid=11"
    },
    {
      "chapterUid": 12,
      "chapterIdx": 12,
      "title": "二、面临绝后",
      "level": 2,
      "wordCount": 2777,
      "price": 0,
      "paid": 0,
      "isMPChapter": 0,
      "anchors": [],
      "appLink": "weread://reading?bId=CB_CKd9vz9vx6ti71y71E21O0YE&chapterUid=12",
      "webLink": "https://weread.qq.com/web/reader/87542583643425f434b6439767a39767836746937317937314532314f3059455b6?chapterUid=12"
    },
    {
      "chapterUid": 13,
      "chapterIdx": 13,
      "title": "三、从县中小吏到地方名流",
      "level": 2,
      "wordCount": 1550,
      "price": 0,
      "paid": 0,
      "isMPChapter": 0,
      "anchors": [],
      "appLink": "weread://reading?bId=CB_CKd9vz9vx6ti71y71E21O0YE&chapterUid=13",
      "webLink": "https://weread.qq.com/web/reader/87542583643425f434b6439767a39767836746937317937314532314f3059455b6?chapterUid=13"
    },
    {
      "chapterUid": 14,
      "chapterIdx": 14,
      "title": "四、第四代早期",
      "level": 2,
      "wordCount": 1323,
      "price": 0,
      "paid": 0,
      "isMPChapter": 0,
      "anchors": [],
      "appLink": "weread://reading?bId=CB_CKd9vz9vx6ti71y71E21O0YE&chapterUid=14",
      "webLink": "https://weread.qq.com/web/reader/87542583643425f434b6439767a39767836746937317937314532314f3059455b6?chapterUid=14"
    },
    {
      "chapterUid": 15,
      "chapterIdx": 15,
      "title": "五、史才进京",
      "level": 2,
      "wordCount": 3190,
      "price": 0,
      "paid": 0,
      "isMPChapter": 0,
      "anchors": [],
      "appLink": "weread://reading?bId=CB_CKd9vz9vx6ti71y71E21O0YE&chapterUid=15",
      "webLink": "https://weread.qq.com/web/reader/87542583643425f434b6439767a39767836746937317937314532314f3059455b6?chapterUid=15"
    },
    {
      "chapterUid": 16,
      "chapterIdx": 16,
      "title": "六、第四代概况",
      "level": 2,
      "wordCount": 2561,
      "price": 0,
      "paid": 0,
      "isMPChapter": 0,
      "anchors": [],
      "appLink": "weread://reading?bId=CB_CKd9vz9vx6ti71y71E21O0YE&chapterUid=16",
      "webLink": "https://weread.qq.com/web/reader/87542583643425f434b6439767a39767836746937317937314532314f3059455b6?chapterUid=16"
    },
    {
      "chapterUid": 17,
      "chapterIdx": 17,
      "title": "第三章 植根皇城",
      "level": 1,
      "wordCount": 192,
      "price": 0,
      "paid": 0,
      "isMPChapter": 0,
      "anchors": [],
      "appLink": "weread://reading?bId=CB_CKd9vz9vx6ti71y71E21O0YE&chapterUid=17",
      "webLink": "https://weread.qq.com/web/reader/87542583643425f434b6439767a39767836746937317937314532314f3059455b6?chapterUid=17"
    },
    {
      "chapterUid": 18,
      "chapterIdx": 18,
      "title": "一、走向权力",
      "level": 2,
      "wordCount": 1803,
      "price": 0,
      "paid": 0,
      "isMPChapter": 0,
      "anchors": [],
      "appLink": "weread://reading?bId=CB_CKd9vz9vx6ti71y71E21O0YE&chapterUid=18",
      "webLink": "https://weread.qq.com/web/reader/87542583643425f434b6439767a39767836746937317937314532314f3059455b6?chapterUid=18"
    },
    {
      "chapterUid": 19,
      "chapterIdx": 19,
      "title": "二、新君即位",
      "level": 2,
      "wordCount": 1681,
      "price": 0,
      "paid": 0,
      "isMPChapter": 0,
      "anchors": [],
      "appLink": "weread://reading?bId=CB_CKd9vz9vx6ti71y71E21O0YE&chapterUid=19",
      "webLink": "https://weread.qq.com/web/reader/87542583643425f434b6439767a39767836746937317937314532314f3059455b6?chapterUid=19"
    },
    {
      "chapterUid": 20,
      "chapterIdx": 20,
      "title": "三、史浩的和战立场",
      "level": 2,
      "wordCount": 5539,
      "price": 0,
      "paid": 0,
      "isMPChapter": 0,
      "anchors": [],
      "appLink": "weread://reading?bId=CB_CKd9vz9vx6ti71y71E21O0YE&chapterUid=20",
      "webLink": "https://weread.qq.com/web/reader/87542583643425f434b6439767a39767836746937317937314532314f3059455b6?chapterUid=20"
    },
    {
      "chapterUid": 21,
      "chapterIdx": 21,
      "title": "四、丞相起复",
      "level": 2,
      "wordCount": 4547,
      "price": 0,
      "paid": 0,
      "isMPChapter": 0,
      "anchors": [],
      "appLink": "weread://reading?bId=CB_CKd9vz9vx6ti71y71E21O0YE&chapterUid=21",
      "webLink": "https://weread.qq.com/web/reader/87542583643425f434b6439767a39767836746937317937314532314f3059455b6?chapterUid=21"
    },
    {
      "chapterUid": 22,
      "chapterIdx": 22,
      "title": "五、史浩翼下的史氏",
      "level": 2,
      "wordCount": 9859,
      "price": 0,
      "paid": 0,
      "isMPChapter": 0,
      "anchors": [],
      "appLink": "weread://reading?bId=CB_CKd9vz9vx6ti71y71E21O0YE&chapterUid=22",
      "webLink": "https://weread.qq.com/web/reader/87542583643425f434b6439767a39767836746937317937314532314f3059455b6?chapterUid=22"
    },
    {
      "chapterUid": 23,
      "chapterIdx": 23,
      "title": "第四章 春华秋盛",
      "level": 1,
      "wordCount": 1838,
      "price": 0,
      "paid": 0,
      "isMPChapter": 0,
      "anchors": [],
      "appLink": "weread://reading?bId=CB_CKd9vz9vx6ti71y71E21O0YE&chapterUid=23",
      "webLink": "https://weread.qq.com/web/reader/87542583643425f434b6439767a39767836746937317937314532314f3059455b6?chapterUid=23"
    },
    {
      "chapterUid": 24,
      "chapterIdx": 24,
      "title": "一、早年的史弥远",
      "level": 2,
      "wordCount": 1848,
      "price": 0,
      "paid": 0,
      "isMPChapter": 0,
      "anchors": [],
      "appLink": "weread://reading?bId=CB_CKd9vz9vx6ti71y71E21O0YE&chapterUid=24",
      "webLink": "https://weread.qq.com/web/reader/87542583643425f434b6439767a39767836746937317937314532314f3059455b6?chapterUid=24"
    },
    {
      "chapterUid": 25,
      "chapterIdx": 25,
      "title": "二、韩胄之死",
      "level": 2,
      "wordCount": 6684,
      "price": 0,
      "paid": 0,
      "isMPChapter": 0,
      "anchors": [],
      "appLink": "weread://reading?bId=CB_CKd9vz9vx6ti71y71E21O0YE&chapterUid=25",
      "webLink": "https://weread.qq.com/web/reader/87542583643425f434b6439767a39767836746937317937314532314f3059455b6?chapterUid=25"
    },
    {
      "chapterUid": 26,
      "chapterIdx": 26,
      "title": "三、地位日固",
      "level": 2,
      "wordCount": 2208,
      "price": 0,
      "paid": 0,
      "isMPChapter": 0,
      "anchors": [],
      "appLink": "weread://reading?bId=CB_CKd9vz9vx6ti71y71E21O0YE&chapterUid=26",
      "webLink": "https://weread.qq.com/web/reader/87542583643425f434b6439767a39767836746937317937314532314f3059455b6?chapterUid=26"
    },
    {
      "chapterUid": 27,
      "chapterIdx": 27,
      "title": "四、皇子殇逝",
      "level": 2,
      "wordCount": 7341,
      "price": 0,
      "paid": 0,
      "isMPChapter": 0,
      "anchors": [],
      "appLink": "weread://reading?bId=CB_CKd9vz9vx6ti71y71E21O0YE&chapterUid=27",
      "webLink": "https://weread.qq.com/web/reader/87542583643425f434b6439767a39767836746937317937314532314f3059455b6?chapterUid=27"
    },
    {
      "chapterUid": 28,
      "chapterIdx": 28,
      "title": "五、边界政策",
      "level": 2,
      "wordCount": 4373,
      "price": 0,
      "paid": 0,
      "isMPChapter": 0,
      "anchors": [],
      "appLink": "weread://reading?bId=CB_CKd9vz9vx6ti71y71E21O0YE&chapterUid=28",
      "webLink": "https://weread.qq.com/web/reader/87542583643425f434b6439767a39767836746937317937314532314f3059455b6?chapterUid=28"
    },
    {
      "chapterUid": 29,
      "chapterIdx": 29,
      "title": "六、卫王晚年",
      "level": 2,
      "wordCount": 5388,
      "price": 0,
      "paid": 0,
      "isMPChapter": 0,
      "anchors": [],
      "appLink": "weread://reading?bId=CB_CKd9vz9vx6ti71y71E21O0YE&chapterUid=29",
      "webLink": "https://weread.qq.com/web/reader/87542583643425f434b6439767a39767836746937317937314532314f3059455b6?chapterUid=29"
    },
    {
      "chapterUid": 30,
      "chapterIdx": 30,
      "title": "七、第六代概要",
      "level": 2,
      "wordCount": 5298,
      "price": 0,
      "paid": 0,
      "isMPChapter": 0,
      "anchors": [],
      "appLink": "weread://reading?bId=CB_CKd9vz9vx6ti71y71E21O0YE&chapterUid=30",
      "webLink": "https://weread.qq.com/web/reader/87542583643425f434b6439767a39767836746937317937314532314f3059455b6?chapterUid=30"
    },
    {
      "chapterUid": 31,
      "chapterIdx": 31,
      "title": "八、本章余论",
      "level": 2,
      "wordCount": 13719,
      "price": 0,
      "paid": 0,
      "isMPChapter": 0,
      "anchors": [],
      "appLink": "weread://reading?bId=CB_CKd9vz9vx6ti71y71E21O0YE&chapterUid=31",
      "webLink": "https://weread.qq.com/web/reader/87542583643425f434b6439767a39767836746937317937314532314f3059455b6?chapterUid=31"
    },
    {
      "chapterUid": 32,
      "chapterIdx": 32,
      "title": "第五章 落日余晖",
      "level": 1,
      "wordCount": 3981,
      "price": 0,
      "paid": 0,
      "isMPChapter": 0,
      "anchors": [
        {
          "title": "一、理宗一朝",
          "anchor": "sigil_toc_id_1",
          "level": 2
        }
      ],
      "appLink": "weread://reading?bId=CB_CKd9vz9vx6ti71y71E21O0YE&chapterUid=32",
      "webLink": "https://weread.qq.com/web/reader/87542583643425f434b6439767a39767836746937317937314532314f3059455b6?chapterUid=32"
    },
    {
      "chapterUid": 33,
      "chapterIdx": 33,
      "title": "二、长房子孙",
      "level": 2,
      "wordCount": 4634,
      "price": 0,
      "paid": 0,
      "isMPChapter": 0,
      "anchors": [],
      "appLink": "weread://reading?bId=CB_CKd9vz9vx6ti71y71E21O0YE&chapterUid=33",
      "webLink": "https://weread.qq.com/web/reader/87542583643425f434b6439767a39767836746937317937314532314f3059455b6?chapterUid=33"
    },
    {
      "chapterUid": 34,
      "chapterIdx": 34,
      "title": "三、一门三相",
      "level": 2,
      "wordCount": 9694,
      "price": 0,
      "paid": 0,
      "isMPChapter": 0,
      "anchors": [],
      "appLink": "weread://reading?bId=CB_CKd9vz9vx6ti71y71E21O0YE&chapterUid=34",
      "webLink": "https://weread.qq.com/web/reader/87542583643425f434b6439767a39767836746937317937314532314f3059455b6?chapterUid=34"
    },
    {
      "chapterUid": 35,
      "chapterIdx": 35,
      "title": "四、三房族人",
      "level": 2,
      "wordCount": 2020,
      "price": 0,
      "paid": 0,
      "isMPChapter": 0,
      "anchors": [],
      "appLink": "weread://reading?bId=CB_CKd9vz9vx6ti71y71E21O0YE&chapterUid=35",
      "webLink": "https://weread.qq.com/web/reader/87542583643425f434b6439767a39767836746937317937314532314f3059455b6?chapterUid=35"
    },
    {
      "chapterUid": 36,
      "chapterIdx": 36,
      "title": "五、本章余论",
      "level": 2,
      "wordCount": 9093,
      "price": 0,
      "paid": 0,
      "isMPChapter": 0,
      "anchors": [],
      "appLink": "weread://reading?bId=CB_CKd9vz9vx6ti71y71E21O0YE&chapterUid=36",
      "webLink": "https://weread.qq.com/web/reader/87542583643425f434b6439767a39767836746937317937314532314f3059455b6?chapterUid=36"
    },
    {
      "chapterUid": 37,
      "chapterIdx": 37,
      "title": "尾声 曲终人散",
      "level": 1,
      "wordCount": 7173,
      "price": 0,
      "paid": 0,
      "isMPChapter": 0,
      "anchors": [],
      "appLink": "weread://reading?bId=CB_CKd9vz9vx6ti71y71E21O0YE&chapterUid=37",
      "webLink": "https://weread.qq.com/web/reader/87542583643425f434b6439767a39767836746937317937314532314f3059455b6?chapterUid=37"
    },
    {
      "chapterUid": 38,
      "chapterIdx": 38,
      "title": "附录一 四明史氏族系图",
      "level": 1,
      "wordCount": 53,
      "price": 0,
      "paid": 0,
      "isMPChapter": 0,
      "anchors": [],
      "appLink": "weread://reading?bId=CB_CKd9vz9vx6ti71y71E21O0YE&chapterUid=38",
      "webLink": "https://weread.qq.com/web/reader/87542583643425f434b6439767a39767836746937317937314532314f3059455b6?chapterUid=38"
    },
    {
      "chapterUid": 39,
      "chapterIdx": 39,
      "title": "附录二 南宋丞相的地理分布",
      "level": 1,
      "wordCount": 4824,
      "price": 0,
      "paid": 0,
      "isMPChapter": 0,
      "anchors": [],
      "appLink": "weread://reading?bId=CB_CKd9vz9vx6ti71y71E21O0YE&chapterUid=39",
      "webLink": "https://weread.qq.com/web/reader/87542583643425f434b6439767a39767836746937317937314532314f3059455b6?chapterUid=39"
    },
    {
      "chapterUid": 40,
      "chapterIdx": 40,
      "title": "附录三 史氏部分族人的名单和政治成就",
      "level": 1,
      "wordCount": 5711,
      "price": 0,
      "paid": 0,
      "isMPChapter": 0,
      "anchors": [],
      "appLink": "weread://reading?bId=CB_CKd9vz9vx6ti71y71E21O0YE&chapterUid=40",
      "webLink": "https://weread.qq.com/web/reader/87542583643425f434b6439767a39767836746937317937314532314f3059455b6?chapterUid=40"
    },
    {
      "chapterUid": 41,
      "chapterIdx": 41,
      "title": "附录四 历史学上对南宋成见的形成及其演化 ——以史弥远为例",
      "level": 1,
      "wordCount": 879,
      "price": 0,
      "paid": 0,
      "isMPChapter": 0,
      "anchors": [],
      "appLink": "weread://reading?bId=CB_CKd9vz9vx6ti71y71E21O0YE&chapterUid=41",
      "webLink": "https://weread.qq.com/web/reader/87542583643425f434b6439767a39767836746937317937314532314f3059455b6?chapterUid=41"
    },
    {
      "chapterUid": 42,
      "chapterIdx": 42,
      "title": "一、嘉定十七年（1224）理宗继位：官方的记述",
      "level": 2,
      "wordCount": 3883,
      "price": 0,
      "paid": 0,
      "isMPChapter": 0,
      "anchors": [],
      "appLink": "weread://reading?bId=CB_CKd9vz9vx6ti71y71E21O0YE&chapterUid=42",
      "webLink": "https://weread.qq.com/web/reader/87542583643425f434b6439767a39767836746937317937314532314f3059455b6?chapterUid=42"
    },
    {
      "chapterUid": 43,
      "chapterIdx": 43,
      "title": "二、非官方史料的中立性",
      "level": 2,
      "wordCount": 3183,
      "price": 0,
      "paid": 0,
      "isMPChapter": 0,
      "anchors": [],
      "appLink": "weread://reading?bId=CB_CKd9vz9vx6ti71y71E21O0YE&chapterUid=43",
      "webLink": "https://weread.qq.com/web/reader/87542583643425f434b6439767a39767836746937317937314532314f3059455b6?chapterUid=43"
    },
    {
      "chapterUid": 44,
      "chapterIdx": 44,
      "title": "三、教化之兴：明朝的演绎",
      "level": 2,
      "wordCount": 10226,
      "price": 0,
      "paid": 0,
      "isMPChapter": 0,
      "anchors": [],
      "appLink": "weread://reading?bId=CB_CKd9vz9vx6ti71y71E21O0YE&chapterUid=44",
      "webLink": "https://weread.qq.com/web/reader/87542583643425f434b6439767a39767836746937317937314532314f3059455b6?chapterUid=44"
    },
    {
      "chapterUid": 45,
      "chapterIdx": 45,
      "title": "四、清朝的重新评价：一些盖棺之论",
      "level": 2,
      "wordCount": 11174,
      "price": 0,
      "paid": 0,
      "isMPChapter": 0,
      "anchors": [],
      "appLink": "weread://reading?bId=CB_CKd9vz9vx6ti71y71E21O0YE&chapterUid=45",
      "webLink": "https://weread.qq.com/web/reader/87542583643425f434b6439767a39767836746937317937314532314f3059455b6?chapterUid=45"
    },
    {
      "chapterUid": 46,
      "chapterIdx": 46,
      "title": "参考文献",
      "level": 1,
      "wordCount": 2816,
      "price": 0,
      "paid": 0,
      "isMPChapter": 0,
      "anchors": [
        {
          "title": "一、中文古籍文献",
          "anchor": "sigil_toc_id_2",
          "level": 2
        }
      ],
      "appLink": "weread://reading?bId=CB_CKd9vz9vx6ti71y71E21O0YE&chapterUid=46",
      "webLink": "https://weread.qq.com/web/reader/87542583643425f434b6439767a39767836746937317937314532314f3059455b6?chapterUid=46"
    },
    {
      "chapterUid": 47,
      "chapterIdx": 47,
      "title": "二、英文著述",
      "level": 2,
      "wordCount": 5469,
      "price": 0,
      "paid": 0,
      "isMPChapter": 0,
      "anchors": [],
      "appLink": "weread://reading?bId=CB_CKd9vz9vx6ti71y71E21O0YE&chapterUid=47",
      "webLink": "https://weread.qq.com/web/reader/87542583643425f434b6439767a39767836746937317937314532314f3059455b6?chapterUid=47"
    },
    {
      "chapterUid": 48,
      "chapterIdx": 48,
      "title": "三、中文及日文著述",
      "level": 2,
      "wordCount": 2348,
      "price": 0,
      "paid": 0,
      "isMPChapter": 0,
      "anchors": [],
      "appLink": "weread://reading?bId=CB_CKd9vz9vx6ti71y71E21O0YE&chapterUid=48",
      "webLink": "https://weread.qq.com/web/reader/87542583643425f434b6439767a39767836746937317937314532314f3059455b6?chapterUid=48"
    },
    {
      "chapterUid": 49,
      "chapterIdx": 49,
      "title": "译后记",
      "level": 1,
      "wordCount": 2487,
      "price": 0,
      "paid": 0,
      "isMPChapter": 0,
      "anchors": [],
      "appLink": "weread://reading?bId=CB_CKd9vz9vx6ti71y71E21O0YE&chapterUid=49",
      "webLink": "https://weread.qq.com/web/reader/87542583643425f434b6439767a39767836746937317937314532314f3059455b6?chapterUid=49"
    }
  ],
  "content": [
    {
      "chapterUid": 2,
      "chapterTitle": "悼念我的恩师刘子健教授(1)",
      "items": [
        {
          "type": "review",
          "reviewId": "32618646_871VPJdLp",
          "range": "882-886",
          "chapterName": "悼念我的恩师刘子健教授(1)",
          "content": "zī zī bù juàn\n\n勤奋努力，不知疲倦。",
          "abstract": "孜孜不倦",
          "star": -1,
          "createTime": 1771481931,
          "createTimeFormatted": "2026-02-19 14:18:51",
          "isFinish": false,
          "chapterUid": 2
        }
      ]
    }
  ],
  "bookReviews": [],
  "hotBookmarks": [],
  "readProgress": {
    "chapterUid": 2,
    "chapterOffset": 553,
    "progress": 0,
    "updateTime": 1771481933,
    "recordReadingTime": 0,
    "finishTime": ""
  }
}